{"nodes": [{"id": "src_utils_logger_ts", "label": "logger.ts", "file_type": "code", "source_file": "src/utils/logger.ts", "source_location": "L1"}, {"id": "logger_exit", "label": "exit()", "file_type": "code", "source_file": "src/utils/logger.ts", "source_location": "L18"}], "edges": [{"source": "src_utils_logger_ts", "target": "node_process", "relation": "imports_from", "confidence": "EXTRACTED", "source_file": "src/utils/logger.ts", "source_location": "L1", "weight": 1.0}, {"source": "src_utils_logger_ts", "target": "logger_exit", "relation": "contains", "confidence": "EXTRACTED", "source_file": "src/utils/logger.ts", "source_location": "L18", "weight": 1.0}]}